pytest_django_cache_xdist.py
pytest_django_cache_xdist-0.1.0.dist-info/LICENSE
pytest_django_cache_xdist-0.1.0.dist-info/METADATA
pytest_django_cache_xdist-0.1.0.dist-info/WHEEL
pytest_django_cache_xdist-0.1.0.dist-info/entry_points.txt
pytest_django_cache_xdist-0.1.0.dist-info/top_level.txt
pytest_django_cache_xdist-0.1.0.dist-info/RECORD
